bip32utils/BIP32Key.py
bip32utils/Base58.py
bip32utils/__init__.py
bip32utilz-0.3.post3.data/scripts/bip32gen
bip32utilz-0.3.post3.dist-info/METADATA
bip32utilz-0.3.post3.dist-info/RECORD
bip32utilz-0.3.post3.dist-info/WHEEL
bip32utilz-0.3.post3.dist-info/top_level.txt
