Metadata-Version: 2.1
Name: bip32utilz
Version: 0.3.post3
Summary: Utilities for generating and using Bitcoin Hierarchical Deterministic wallets (BIP0032).
Home-page: http://github.com/prusnak/bip32utils
Author: Johnathan Corgan, Corgan Labs
Author-email: johnathan@corganlabs.com
Maintainer: Pavol Rusnak
Maintainer-email: stick@gk2.sk
License: MIT
Platform: UNKNOWN
Requires-Dist: ecdsa
